llmer/__init__.py
llmer/__version__.py
llmer/file.py
llmer/parser.py
llmer/prompt.py
llmer/server.py
llmer/model/__init__.py
llmer/model/azure_openai.py
llmer/model/base.py
llmer/model/openai.py
llmer/parallel/__init__.py
llmer/parallel/async_executor.py
llmer/parallel/async_parallel.py
llmer/parallel/base.py
llmer/parallel/multi_thread.py
llmer/parallel/thread_pool.py
llmer/runtime/__init__.py
llmer/runtime/context.py
llmer/runtime/exceptions.py
test/__init__.py
test/test.py
test/test_llmer_model.py
test/test_llmer_parallel.py
llmer-1.0.3.dist-info/METADATA
llmer-1.0.3.dist-info/WHEEL
llmer-1.0.3.dist-info/top_level.txt
llmer-1.0.3.dist-info/RECORD
