Metadata-Version: 2.1
Name: llmer
Version: 1.0.3
Summary: llmer is a lightweight Python library designed to streamline the development of applications leveraging large language models (LLMs). It provides high-level APIs and utilities for parallel processing, runtime management, file handling, and prompt generation, reducing the overhead of repetitive tasks.
Home-page: https://github.com/pydaxing/llmer
Author: pydaxing
Author-email: pydaxing@gmail.com
Keywords: llmer leveraging large language models
Classifier: Development Status :: 5 - Production/Stable
Classifier: Intended Audience :: Developers
Classifier: License :: OSI Approved :: MIT License
Classifier: Programming Language :: Python
Classifier: Programming Language :: Python :: 3
Classifier: Programming Language :: Python :: 3.6
Classifier: Programming Language :: Python :: 3.7
Classifier: Programming Language :: Python :: 3.8
Classifier: Programming Language :: Python :: 3.9
Classifier: Programming Language :: Python :: 3.10
Classifier: Programming Language :: Python :: 3.11
Classifier: Operating System :: OS Independent
Classifier: Topic :: Software Development
Classifier: Topic :: Software Development :: Libraries
Classifier: Topic :: Software Development :: Libraries :: Python Modules
Classifier: Typing :: Typed
Requires-Python: >=3.6
Requires-Dist: jsonlines>=4.0.0
Requires-Dist: PyYAML>=6.0.2
Requires-Dist: setuptools>=75.6.0
Requires-Dist: tqdm>=4.67.1
Requires-Dist: openai>=1.56.1
Requires-Dist: fastapi>=0.115.6
Requires-Dist: uvicorn>=0.32.1
